{
    "id":"ab751dbb-276b-46fc-b52a-510b0a80e252",
    "resourceType": "Observation",
    "status": "final",
    "code":
    {
        "coding": [
            {
                "system": "http://veterinaria-equipo-b.org/ValueSet/TpoPelajeVs",
                "code": "CORTO",
                "display": "Corto"
            }
        ]
    },
    "subject": {
        "reference": "Patient/78a24bfb-6796-4fae-9103-ca401cd6629d"
    },
    "effective": "2024-07-23",
    "performer": {
        "reference": "Practitioner/7571c9e6-cdc8-4024-85cc-6f18fe7b05b7"
    }
}